Orm2DocZhCn/README.md
Orm2DocZhCn/__init__.py
Orm2DocZhCn/__main__.py
Orm2DocZhCn/file.epub
Orm2DocZhCn/index.html
Orm2DocZhCn/css/__init__.py
Orm2DocZhCn/css/annotations.css
Orm2DocZhCn/css/main.css
Orm2DocZhCn/css/normalize.css
Orm2DocZhCn/css/popup.css
Orm2DocZhCn/font/__init__.py
Orm2DocZhCn/font/fontello.eot
Orm2DocZhCn/font/fontello.svg
Orm2DocZhCn/font/fontello.ttf
Orm2DocZhCn/font/fontello.woff
Orm2DocZhCn/img/__init__.py
Orm2DocZhCn/img/annotator-glyph-sprite.png
Orm2DocZhCn/img/annotator-icon-sprite.png
Orm2DocZhCn/img/apple-touch-icon.png
Orm2DocZhCn/img/cancelfullscreen.png
Orm2DocZhCn/img/close.png
Orm2DocZhCn/img/fullscreen.png
Orm2DocZhCn/img/loader.gif
Orm2DocZhCn/img/menu-icon.png
Orm2DocZhCn/img/save.png
Orm2DocZhCn/img/saved.png
Orm2DocZhCn/img/settings-s.png
Orm2DocZhCn/img/settings.png
Orm2DocZhCn/img/star.png
Orm2DocZhCn/js/__init__.py
Orm2DocZhCn/js/epub.js
Orm2DocZhCn/js/epub.min.js
Orm2DocZhCn/js/epub.min.map
Orm2DocZhCn/js/hooks.min.js
Orm2DocZhCn/js/hooks.min.map
Orm2DocZhCn/js/reader.js
Orm2DocZhCn/js/reader.js.map
Orm2DocZhCn/js/reader.min.js
Orm2DocZhCn/js/reader.min.map
Orm2DocZhCn/js/hooks/__init__.py
Orm2DocZhCn/js/hooks/extensions/__init__.py
Orm2DocZhCn/js/hooks/extensions/highlight.js
Orm2DocZhCn/js/libs/__init__.py
Orm2DocZhCn/js/libs/jquery.min.js
Orm2DocZhCn/js/libs/localforage.min.js
Orm2DocZhCn/js/libs/screenfull.js
Orm2DocZhCn/js/libs/screenfull.min.js
Orm2DocZhCn/js/libs/zip.min.js
Orm2DocZhCn/js/plugins/__init__.py
Orm2DocZhCn/js/plugins/hypothesis.js
Orm2DocZhCn/js/plugins/search.js
orm2_doc_zh_cn-2024.3.1.0.dist-info/METADATA
orm2_doc_zh_cn-2024.3.1.0.dist-info/WHEEL
orm2_doc_zh_cn-2024.3.1.0.dist-info/entry_points.txt
orm2_doc_zh_cn-2024.3.1.0.dist-info/top_level.txt
orm2_doc_zh_cn-2024.3.1.0.dist-info/RECORD
